svg_turtle/__init__.py
svg_turtle/about.py
svg_turtle/canvas.py
svg_turtle/ipython_turtle.py
svg_turtle/svg_turtle.py
svg_turtle-1.0.0.dist-info/LICENSE
svg_turtle-1.0.0.dist-info/METADATA
svg_turtle-1.0.0.dist-info/WHEEL
svg_turtle-1.0.0.dist-info/top_level.txt
svg_turtle-1.0.0.dist-info/RECORD
