Metadata-Version: 2.1
Name: svg_turtle
Version: 1.0.0
Summary: Use the Python turtle to write SVG files. With optional IPython integration.
Home-page: https://donkirkby.github.io/svg-turtle
Author: Don Kirkby
Author-email: donkirkby@gmail.com
Project-URL: Source, https://github.com/donkirkby/svg-turtle
Project-URL: Issues, https://github.com/donkirkby/svg-turtle/issues
Classifier: Intended Audience :: Developers
Classifier: Topic :: Multimedia :: Graphics
Classifier: Programming Language :: Python :: 3.8
Classifier: Programming Language :: Python :: 3.9
Classifier: Programming Language :: Python :: 3.10
Classifier: Programming Language :: Python :: 3.11
Classifier: Programming Language :: Python :: 3.12
Classifier: Programming Language :: Python :: 3.13
Classifier: License :: OSI Approved :: MIT License
Classifier: Operating System :: OS Independent
Classifier: Development Status :: 5 - Production/Stable
License-File: LICENSE
Requires-Dist: svgwrite
Provides-Extra: ipython
Requires-Dist: ipython; extra == "ipython"
